{"postalCode":"7713311","addresses":[{"prefectureCode":"36","ja":{"prefecture":"徳島県","address1":"名西郡神山町","address2":"神領","address3":"","address4":""},"kana":{"prefecture":"トクシマケン","address1":"ミョウザイグンカミヤマチョウ","address2":"ジンリョウ","address3":"","address4":""},"en":{"prefecture":"Tokushima","address1":"Kamiyama-cho, Myozai-gun","address2":"Jinryo","address3":"","address4":""}},{"prefectureCode":"36","ja":{"prefecture":"徳島県","address1":"名西郡神山町","address2":"神領","address3":"","address4":""},"kana":{"prefecture":"トクシマケン","address1":"ミョウザイグンカミヤマチョウ","address2":"ジンリョウ","address3":"","address4":""},"en":{"prefecture":"Tokushima","address1":"Kamiyama-cho, Myozai-gun","address2":"Jinryo","address3":"","address4":""}},{"prefectureCode":"36","ja":{"prefecture":"徳島県","address1":"名西郡神山町","address2":"神領","address3":"","address4":""},"kana":{"prefecture":"トクシマケン","address1":"ミョウザイグンカミヤマチョウ","address2":"ジンリョウ","address3":"","address4":""},"en":{"prefecture":"Tokushima","address1":"Kamiyama-cho, Myozai-gun","address2":"Jinryo","address3":"","address4":""}},{"prefectureCode":"36","ja":{"prefecture":"徳島県","address1":"名西郡神山町","address2":"神領","address3":"","address4":""},"kana":{"prefecture":"トクシマケン","address1":"ミョウザイグンカミヤマチョウ","address2":"ジンリョウ","address3":"","address4":""},"en":{"prefecture":"Tokushima","address1":"Kamiyama-cho, Myozai-gun","address2":"Jinryo","address3":"","address4":""}},{"prefectureCode":"36","ja":{"prefecture":"徳島県","address1":"名西郡神山町","address2":"神領","address3":"","address4":""},"kana":{"prefecture":"トクシマケン","address1":"ミョウザイグンカミヤマチョウ","address2":"ジンリョウ","address3":"","address4":""},"en":{"prefecture":"Tokushima","address1":"Kamiyama-cho, Myozai-gun","address2":"Jinryo","address3":"","address4":""}},{"prefectureCode":"36","ja":{"prefecture":"徳島県","address1":"名西郡神山町","address2":"神領","address3":"","address4":""},"kana":{"prefecture":"トクシマケン","address1":"ミョウザイグンカミヤマチョウ","address2":"ジンリョウ","address3":"","address4":""},"en":{"prefecture":"Tokushima","address1":"Kamiyama-cho, Myozai-gun","address2":"Jinryo","address3":"","address4":""}},{"prefectureCode":"36","ja":{"prefecture":"徳島県","address1":"名西郡神山町","address2":"神領","address3":"","address4":""},"kana":{"prefecture":"トクシマケン","address1":"ミョウザイグンカミヤマチョウ","address2":"ジンリョウ","address3":"","address4":""},"en":{"prefecture":"Tokushima","address1":"Kamiyama-cho, Myozai-gun","address2":"Jinryo","address3":"","address4":""}}]}