{"postalCode":"9390544","addresses":[{"prefectureCode":"16","ja":{"prefecture":"富山県","address1":"富山市","address2":"水橋上砂子坂","address3":"","address4":""},"kana":{"prefecture":"トヤマケン","address1":"トヤマシ","address2":"ミズハシカミスナゴザカ","address3":"","address4":""},"en":{"prefecture":"Toyama","address1":"Toyama-shi","address2":"Mizuhashikamisunagozaka","address3":"","address4":""}},{"prefectureCode":"16","ja":{"prefecture":"富山県","address1":"富山市","address2":"水橋下砂子坂","address3":"","address4":""},"kana":{"prefecture":"トヤマケン","address1":"トヤマシ","address2":"ミズハシシモスナゴザカ","address3":"","address4":""},"en":{"prefecture":"Toyama","address1":"Toyama-shi","address2":"Mizuhashishimosunagozaka","address3":"","address4":""}},{"prefectureCode":"16","ja":{"prefecture":"富山県","address1":"富山市","address2":"水橋下砂子坂新","address3":"","address4":""},"kana":{"prefecture":"トヤマケン","address1":"トヤマシ","address2":"ミズハシシモスナゴザカシン","address3":"","address4":""},"en":{"prefecture":"Toyama","address1":"Toyama-shi","address2":"Mizuhashishimosunagozakashin","address3":"","address4":""}}]}